froshki
