Metadata-Version: 1.0
Name: froshki
Version: 0.4.3
Summary: simple and poor object data mapper library
Home-page: https://github.com/drowse314-dev-ymat/froshki
Author: drowse314-dev-ymat
Author-email: drowse314@gmail.com
License: BSD
Keywords: form forms object data mapper schema validation
Platform: any
Classifier: Development Status :: 3 - Alpha
Classifier: Intended Audience :: Developers
Classifier: License :: OSI Approved :: BSD License
Classifier: Operating System :: OS Independent
Classifier: Programming Language :: Python :: 2.7
Classifier: Programming Language :: Python :: 3
Classifier: Topic :: Software Development :: Libraries
Classifier: Topic :: Utilities
